flask_request_logger/__about__.py
flask_request_logger/__init__.py
flask_request_logger/api.py
flask_request_logger/cli.py
flask_request_logger/database.py
flask_request_logger/models.py
flask_request_logger/request_logger.py
flask_request_logger/schemas.py
flask_request_logger/utils.py
flask_request_logger-0.3.3.dist-info/LICENSE
flask_request_logger-0.3.3.dist-info/METADATA
flask_request_logger-0.3.3.dist-info/WHEEL
flask_request_logger-0.3.3.dist-info/top_level.txt
flask_request_logger-0.3.3.dist-info/RECORD
