Metadata-Version: 2.1
Name: flask-request-logger
Version: 0.3.3
Summary: A Flask extension for recording requests and responses
Home-page: https://github.com/BbsonLin/flask-request-logger
Author: Bobson Lin
Author-email: bobson801104@gmail.com
License: MIT
Keywords: flask logger
Platform: UNKNOWN
Classifier: Development Status :: 3 - Alpha
Classifier: Environment :: Web Environment
Classifier: Framework :: Flask
Classifier: Operating System :: OS Independent
Classifier: Intended Audience :: Developers
Classifier: Programming Language :: Python
Classifier: Programming Language :: Python :: 3
Classifier: Programming Language :: Python :: 3.5
Classifier: Programming Language :: Python :: 3.6
Classifier: Programming Language :: Python :: 3.7
Classifier: Programming Language :: Python :: Implementation :: PyPy
Classifier: Topic :: Software Development :: Libraries :: Python Modules
Classifier: License :: OSI Approved :: MIT License
Requires-Dist: flask (>=1.0.2)
Requires-Dist: flask-sqlalchemy (>=2.3.2)
Requires-Dist: marshmallow-sqlalchemy (>=0.15.0)
